LICENSE
MANIFEST.in
README.md
pyproject.toml
setup.cfg
setup.py
django_docker/README.md
django_docker/__init__.py
django_docker/apps.py
django_docker/permissions.py
django_docker/serializers.py
django_docker/tests.py
django_docker/views.py
django_docker/entrypoint/__init__.py
django_docker/entrypoint/__main__.py
django_docker/entrypoint/commands.py
django_docker/entrypoint/health_check.py
django_docker_entrypoint.egg-info/PKG-INFO
django_docker_entrypoint.egg-info/SOURCES.txt
django_docker_entrypoint.egg-info/dependency_links.txt
django_docker_entrypoint.egg-info/requires.txt
django_docker_entrypoint.egg-info/top_level.txt